[{"contactId":1,"type":"Billing","street":"36646 Kenwood Avenue","zip":"47175","city":"Avdiyivka","country":"Ukraine"},
{"contactId":2,"type":"Billing","street":"34585 1st Way","zip":"47070","city":"Garmisch-Partenkirchen","country":"Germany"},
{"contactId":3,"type":"Billing","street":"614 Ilene Point","zip":"77629","city":"Cabo San Lucas","country":"Mexico"},
{"contactId":4,"type":"Billing","street":"093 Village Green Alley","zip":"29978-1132","city":"Temerluh","country":"Malaysia"},
{"contactId":5,"type":"Billing","street":"302 Hoard Way","zip":"92338","city":"Rheda-Wiedenbr\u00fcck","country":"Germany"},
{"contactId":6,"type":"Billing","street":"4 Butternut Court","zip":"22503","city":"Wakimachi","country":"Japan"},
{"contactId":7,"type":"Billing","street":"626 Crescent Oaks Plaza","zip":"50266-4161","city":"Zhoucun","country":"China"},
{"contactId":8,"type":"Billing","street":"7445 Harper Park","zip":"17443-5208","city":"Nikk\u014d","country":"Japan"},
{"contactId":9,"type":"Billing","street":"5829 5th Way","zip":"62271-0460","city":"Narathiwat","country":"Thailand"},
{"contactId":10,"type":"Billing","street":"1 Kim Junction","zip":"40517","city":"Huanuni","country":"Bolivia"},
{"contactId":11,"type":"Billing","street":"18 Lakeland Trail","zip":"90753","city":"Bruchsal","country":"Germany"},
{"contactId":12,"type":"Billing","street":"1 Pankratz Street","zip":"92130-0925","city":"Ma\u00f3","country":"Spain"},
{"contactId":13,"type":"Billing","street":"62 Shasta Avenue","zip":"38386","city":"Chai Nat","country":"Thailand"},
{"contactId":14,"type":"Billing","street":"22276 Springview Street","zip":"47162","city":"Thohoyandou","country":"South Africa"},
{"contactId":15,"type":"Billing","street":"30 Ryan Park","zip":"33296-1566","city":"Plymouth","country":"United Kingdom"},
{"contactId":16,"type":"Billing","street":"97239 Cherokee Terrace","zip":"46843-5270","city":"Los Realejos","country":"Spain"},
{"contactId":17,"type":"Billing","street":"37974 Annamark Park","zip":"28848","city":"Sar-e Pul","country":"Afghanistan"},
{"contactId":18,"type":"Billing","street":"433 Ohio Terrace","zip":"94055-1330","city":"Gescher","country":"Germany"},
{"contactId":19,"type":"Billing","street":"16 Service Way","zip":"15268-0109","city":"West Albany","country":"United States"},
{"contactId":20,"type":"Billing","street":"29548 Randy Drive","zip":"24659-8010","city":"\u014cnoj\u014d","country":"Japan"},
{"contactId":21,"type":"Billing","street":"7 Bartillon Trail","zip":"18777","city":"Kasongo-Lunda","country":"Democratic Republic of the Congo"},
{"contactId":22,"type":"Billing","street":"207 Grasskamp Parkway","zip":"23424-4539","city":"Tahoua","country":"Niger"},
{"contactId":23,"type":"Billing","street":"4587 Mayer Trail","zip":"35807-0105","city":"Ibirit\u00e9","country":"Brazil"},
{"contactId":24,"type":"Billing","street":"1950 Darwin Drive","zip":"47509-9370","city":"Tobruk","country":"Libya"},
{"contactId":25,"type":"Billing","street":"542 Kropf Crossing","zip":"72992","city":"Jiquilpan de Ju\u00e1rez","country":"Mexico"},
{"contactId":26,"type":"Billing","street":"11 Derek Hill","zip":"52436","city":"P\u00e1tzcuaro","country":"Mexico"},
{"contactId":27,"type":"Billing","street":"60565 Vermont Road","zip":"06602","city":"\u00c1vila","country":"Spain"},
{"contactId":28,"type":"Billing","street":"47 Dahle Lane","zip":"42169-2101","city":"Nakhon Sawan","country":"Thailand"},
{"contactId":29,"type":"Billing","street":"7890 Dakota Terrace","zip":"44567","city":"W\u00fcrselen","country":"Germany"},
{"contactId":30,"type":"Billing","street":"95 International Parkway","zip":"65885","city":"Berkel en Rodenrijs","country":"Netherlands"},
{"contactId":31,"type":"Billing","street":"0 Pepper Wood Road","zip":"15834","city":"Oakdale","country":"United States"},
{"contactId":32,"type":"Billing","street":"46 Bluejay Crossing","zip":"44627-9720","city":"Santa Mar\u00eda Totoltepec","country":"Mexico"},
{"contactId":33,"type":"Billing","street":"5847 Lerdahl Court","zip":"73583-0447","city":"Pitt Meadows","country":"Canada"},
{"contactId":34,"type":"Billing","street":"546 Jana Terrace","zip":"35098","city":"Isanlu Itedoijowa","country":"Nigeria"},
{"contactId":35,"type":"Billing","street":"10 Calypso Trail","zip":"95266-9819","city":"Kampong Chhnang","country":"Cambodia"},
{"contactId":36,"type":"Billing","street":"1214 Rutledge Way","zip":"01298","city":"A\u00efn Taya","country":"Algeria"},
{"contactId":37,"type":"Billing","street":"2730 Swallow Crossing","zip":"35143","city":"Kurume","country":"Japan"},
{"contactId":38,"type":"Billing","street":"611 Bobwhite Road","zip":"89355-2889","city":"Deux-Montagnes","country":"Canada"},
{"contactId":39,"type":"Billing","street":"37 Linden Court","zip":"61419","city":"Farroupilha","country":"Brazil"},
{"contactId":40,"type":"Billing","street":"2 Lyons Junction","zip":"19860","city":"Barueri","country":"Brazil"},
{"contactId":41,"type":"Billing","street":"6714 Canary Trail","zip":"58641","city":"Caxambu","country":"Brazil"},
{"contactId":42,"type":"Billing","street":"399 Rigney Park","zip":"95552","city":"Norak","country":"Tajikistan"},
{"contactId":43,"type":"Billing","street":"5 Hagan Road","zip":"53647","city":"Dori","country":"Burkina Faso"},
{"contactId":44,"type":"Billing","street":"910 Roxbury Street","zip":"99325-4517","city":"Pathum Thani","country":"Thailand"},
{"contactId":45,"type":"Billing","street":"4570 Main Hill","zip":"96638","city":"Malacca","country":"Malaysia"},
{"contactId":46,"type":"Billing","street":"0 Aberg Avenue","zip":"34043","city":"Kampung Simpang Renggam","country":"Malaysia"},
{"contactId":47,"type":"Billing","street":"686 Darwin Alley","zip":"30508-5142","city":"Zipaquir\u00e1","country":"Colombia"},
{"contactId":48,"type":"Billing","street":"5 Forest Dale Park","zip":"23053-4398","city":"Valladolid","country":"Spain"},
{"contactId":49,"type":"Billing","street":"617 Kenwood Crossing","zip":"81593","city":"Roth","country":"Germany"},
{"contactId":50,"type":"Billing","street":"8 Thackeray Circle","zip":"71430-8774","city":"Wiesloch","country":"Germany"}]